cloudflare2loggly.py
setup.py
sftplib.py
cloudflare2loggly.egg-info/PKG-INFO
cloudflare2loggly.egg-info/SOURCES.txt
cloudflare2loggly.egg-info/dependency_links.txt
cloudflare2loggly.egg-info/entry_points.txt
cloudflare2loggly.egg-info/requires.txt
cloudflare2loggly.egg-info/top_level.txt