Metadata-Version: 1.1
Name: cloudflare2loggly
Version: 0.0.2
Summary: Helper for pushing CloudFlare access logs to Loggly
Home-page: https://github.com/ctrlrsf/cloudflare2loggly
Author: Rene Fragoso
Author-email: ctrlrsf@gmail.com
License: MIT
Platform: UNKNOWN
Classifier: Development Status :: 4 - Beta
Classifier: Environment :: Web Environment
Classifier: Intended Audience :: Developers
Classifier: License :: OSI Approved :: MIT License
Classifier: Operating System :: OS Independent
Classifier: Programming Language :: Python :: 2
Classifier: Programming Language :: Python :: 2.7
